Workbook

Sheet 01_ReadMe
A1: RTL LOAN SIZER / PRICER · OPERATIONAL GUIDE
A2: Internal Use Only · Do Not Distribute Without Authorization
A4: HOW TO USE THIS TOOL
B5: STEP 1 — INPUT | C5: Open 02_Inputs. Fill every light-blue cell. Use the dropdowns for Loan Type, Experience Tier, and Term Months. Do not edit any other cells.
B6: STEP 2 — VERIFY | C6: 04_Calc_Engine updates automatically. Review the Eligibility Flags section for any FAIL or EXCEPTION status before generating a quote.
B7: STEP 3 — QUOTE | C7: Navigate to 05_Quote_Summary for the client-ready single-page term sheet. Export via File → Export → Create PDF/XPS.
B8: STEP 4 — SAVE | C8: Save a named copy per deal (e.g., "Smith_Property_2024-01-15.xlsx"). Never overwrite the master template file.
A10: WORKBOOK ARCHITECTURE
B11: 01_ReadMe | C11: Config layer. User guide, admin notes, version log. No fill tab.
B12: 02_Inputs | C12: All data entry here. Light-blue cells are editable; all others are locked. Dropdowns enforced.
B13: 03_Pricing_&_Assumptions | C13: RESTRICTED. Buy rate matrix, leverage caps, fee presets. Must be xlSheetVeryHidden in Originator version (see Admin Actions below).
B14: 04_Calc_Engine | C14: RESTRICTED. All LTV/LTC/pricing/settlement calculations. Must be xlSheetVeryHidden + formula-masked in Originator version.
B15: 05_Quote_Summary | C15: Client-safe output page. All values are formula links from Calc_Engine. No internal pricing data. Designed for single-page PDF export.
A17: ⚠ ADMIN ACTIONS REQUIRED (VBA / MANUAL — OUTSIDE CODE SCOPE)
B18: Sheet Hiding | C18: Alt+F11 → Project Explorer → select 03_Pricing_&_Assumptions and 04_Calc_Engine → Properties panel → Visible = 2 – xlSheetVeryHidden. Cannot be unhidden via right-click.
B19: Workbook Structure Lock | C19: Review → Protect Workbook → Structure. Enter a strong admin password. This prevents sheet insertion, deletion, moving, or unhiding.
B20: Formula Masking | C20: On sheets 03 and 04: Select All Cells (Ctrl+A) → Ctrl+1 → Protection tab → check BOTH Locked and Hidden. Then Review → Protect Sheet with password to activate the masking.
B21: Conditional Formatting (Inputs) | C21: On 02_Inputs: Add CF rules to gray out cells C10 and C11 when C5="Bridge". Formula: =$C$5="Bridge", apply gray fill (#CCCCCC) to C10:C11 to signal those fields are N/A.
B22: Rate Grid Updates | C22: To edit buy rates: unprotect sheet 03 → modify cells C19:I25 only → re-protect. The grid dimensions (rows 6-10 leverage, rows 19-25 grid, cols C-I) must not change.
A24: VERSION HISTORY
B25: Version | C25: Date | D25: Author / Notes
B26: v1.0 | C26: — | D26: Initial build — RTL Loan Sizer Blueprint v1.0

Sheet 02_Inputs
A1: RTL LOAN SIZER / PRICER · DATA INPUTS
A2: Enter all data in the highlighted input cells only. All other cells are locked and protected.
A4: SECTION A — LOAN OVERVIEW
B5: Loan Type | C5: Bridge | D5: text | E5: Dropdown: Bridge / Fix-and-Flip / Light Rehab / Heavy Rehab / Construction
A7: SECTION B — PROPERTY DETAILS
B8: Purchase Price ($) | D8: $#,##0 | E8: Contract purchase price of the target residential property
B9: As-Is Value ($) | D9: $#,##0 | E9: Current appraised "as-is" value before any improvements
B10: Rehab Budget ($) | D10: $#,##0 | E10: Total scope-of-work cost estimate; enter 0 for Bridge loans
B11: After-Repair Value / ARV ($) | D11: $#,##0 | E11: Post-renovation estimated market value; enter 0 for Bridge loans
A13: SECTION C — REQUESTED LOAN TERMS
B14: Requested Loan Amount ($) | D14: $#,##0 | E14: Total gross loan amount requested by the borrower
B15: Proposed Note Rate (Borrower Rate) | D15: 0.00% | E15: Gross interest rate to borrower — enter as decimal (e.g. 0.1050 = 10.50%)
A17: SECTION D — BORROWER RISK PROFILE
B18: FICO Score | D18: 0 | E18: Credit score of the guarantor/primary borrower (300–850)
B19: Experience Tier | D19: text | E19: Borrower's completed deals in past 36 months — select from dropdown
B20: Verified Liquid Assets ($) | D20: $#,##0 | E20: Cash or cash-equivalents verified at time of application
A22: SECTION E — TRANSACTION PARAMETERS
B23: Loan Term (Months) | D23: 0 | E23: Duration of the transitional loan — select from dropdown
B24: Short Interest Days (0–30) | D24: 0 | E24: Number of prepaid short interest days collected at close
A26: INPUT LEGEND
C27: Sample | D27: User-editable input cell (blue text = hardcoded value)
C28: Sample | D28: Locked / calculated — do not edit
B30: ⚠ WIREFRAME: Dynamic graying of Rehab/ARV cells when Loan Type = Bridge requires Conditional Formatting applied manually in Excel UI. See 01_ReadMe → Admin Actions.

Sheet 03_Pricing_&_Assumptions
A1: RTL LOAN SIZER / PRICER · PRICING & ASSUMPTIONS — RESTRICTED: ADMIN ACCESS ONLY
A2: ⚠ In the Originator-Facing version, this sheet must be set to xlSheetVeryHidden via VBA (Alt+F11). See 01_ReadMe → Admin Actions.
A4: SECTION 1 — MAXIMUM LEVERAGE LIMITS BY LOAN TYPE
B5: Loan Type | C5: Max LTV | D5: Max LTC | E5: Max LTARV
B6: Bridge | C6: 0.75 | D6: N/A | E6: N/A
B7: Fix-and-Flip | C7: 0.9 | D7: 0.85 | E7: 0.7
B8: Light Rehab | C8: 0.8 | D8: 0.9 | E8: 0.75
B9: Heavy Rehab | C9: 0.75 | D9: 0.85 | E9: 0.7
B10: Construction | C10: 0.7 | D10: 0.85 | E10: 0.65
A12: SECTION 2 — PROFIT SAFEGUARDS & FEE DEFAULTS
B13: Minimum Spread Floor | C13: 0.025 | D13: [Asm_Min_Spread] | F13: Minimum lender margin over buy rate. Calc_Spread_Status = 'Below Margin' if violated.
B14: Annual Servicing Fee | C14: 0.0025 | D14: [Asm_Serv_Fee_Pct] | F14: Deducted from gross loan at settlement: Loan_Amt × (Fee/12) × Term_Months.
A16: SECTION 3 — BASE BUY RATE PRICING GRID (FICO × LTV Tier Matrix)
B17: MATCH logic (Actual/360): MATCH(FICO, B19:B25, 1) → largest FICO tier ≤ input. MATCH(LTV, C18:I18, 1) → largest LTV tier ≤ Calc_Actual_LTV. INDEX(C19:I25, row, col) retrieves the Buy Rate. N/A cells = combination not offered; Eligibility flag will fire first.
B18: FICO ↓ / LTV → | C18: 0.5 | D18: 0.55 | E18: 0.6 | F18: 0.65 | G18: 0.7 | H18: 0.75 | I18: 0.8
B19: 620 | C19: 0.105 | D19: 0.1075 | E19: 0.11 | F19: 0.115
B20: 640 | C20: 0.0975 | D20: 0.1 | E20: 0.1025 | F20: 0.1075 | G20: 0.1125
B21: 660 | C21: 0.0925 | D21: 0.095 | E21: 0.0975 | F21: 0.1025 | G21: 0.1075 | H21: 0.1125
B22: 680 | C22: 0.0875 | D22: 0.09 | E22: 0.0925 | F22: 0.0975 | G22: 0.1025 | H22: 0.1075 | I22: 0.1125
B23: 700 | C23: 0.0825 | D23: 0.085 | E23: 0.0875 | F23: 0.0925 | G23: 0.0975 | H23: 0.1025 | I23: 0.1075
B24: 720 | C24: 0.08 | D24: 0.0825 | E24: 0.085 | F24: 0.09 | G24: 0.095 | H24: 0.1 | I24: 0.105
B25: 740 | C25: 0.0775 | D25: 0.08 | E25: 0.0825 | F25: 0.0875 | G25: 0.0925 | H25: 0.0975 | I25: 0.1025
B27: ⚠ WIREFRAME: This sheet must be password-protected and set to xlSheetVeryHidden via VBA. Row/column structure (leverage rows 6-10, grid rows 19-25, grid cols C-I) MUST NOT change — Calc_Engine INDEX/MATCH formula ranges are hard-coded against this layout.

Sheet 04_Calc_Engine
A1: RTL LOAN SIZER / PRICER · CALCULATION ENGINE — RESTRICTED: DO NOT DISTRIBUTE
A2: ⚠ All formula cells must be set to Locked+Hidden (Ctrl+1 → Protection), sheet protected, and sheet visibility set to xlSheetVeryHidden via VBA. See 01_ReadMe → Admin Actions.
A4: SECTION 1 — DYNAMIC LEVERAGE CONSTRAINTS (Lookup from Pricing Sheet by Loan Type)
B5: Variable | C5: Calculated Value | D5: Format | E5: Description
B6: Asm_Max_LTV | C6: =IFERROR(INDEX('03_Pricing_&_Assumptions'!$C$6:$C$10,MATCH(TRIM(UPPER('02_Inputs'!$C$5)),TRIM(UPPER('03_Pricing_&_Assumptions'!$B$6:$B$10)),0)),0) -> 0 | D6: 0.00% | E6: Max LTV for the selected loan type; 0 if no match
B7: Asm_Max_LTC | C7: =IFERROR(INDEX('03_Pricing_&_Assumptions'!$D$6:$D$10,MATCH(TRIM(UPPER('02_Inputs'!$C$5)),TRIM(UPPER('03_Pricing_&_Assumptions'!$B$6:$B$10)),0)),"N/A") -> N/A | D7: 0.00% | E7: Max LTC; returns "N/A" string for Bridge (N("N/A")=0 → flag N/A)
B8: Asm_Max_LTARV | C8: =IFERROR(INDEX('03_Pricing_&_Assumptions'!$E$6:$E$10,MATCH(TRIM(UPPER('02_Inputs'!$C$5)),TRIM(UPPER('03_Pricing_&_Assumptions'!$B$6:$B$10)),0)),"N/A") -> N/A | D8: 0.00% | E8: Max LTARV; returns "N/A" string for Bridge
A10: SECTION 2 — LEVERAGE METRICS
B11: Variable | C11: Calculated Value | D11: Format | E11: Description
B12: Calc_Actual_LTV | C12: =IF(N('02_Inputs'!$C$9)=0,0,IFERROR('02_Inputs'!$C$14/'02_Inputs'!$C$9,0)) -> 0 | D12: 0.00% | E12: Loan Amount ÷ As-Is Value
B13: Calc_Actual_LTC | C13: =IF(('02_Inputs'!$C$8+'02_Inputs'!$C$10)=0,0,IFERROR('02_Inputs'!$C$14/('02_Inputs'!$C$8+'02_Inputs'!$C$10),0)) -> 0 | D13: 0.00% | E13: Loan Amount ÷ (Purchase Price + Rehab Budget)
B14: Calc_Actual_LTP | C14: =IF(N('02_Inputs'!$C$8)=0,0,IFERROR('02_Inputs'!$C$14/'02_Inputs'!$C$8,0)) -> 0 | D14: 0.00% | E14: Loan Amount ÷ Purchase Price
B15: Calc_Actual_LTARV | C15: =IF(N('02_Inputs'!$C$11)=0,0,IFERROR('02_Inputs'!$C$14/'02_Inputs'!$C$11,0)) -> 0 | D15: 0.00% | E15: Loan Amount ÷ ARV; returns 0 if ARV field is blank
A17: SECTION 3 — UNDERWRITING FLAGS & GLOBAL ELIGIBILITY
B18: Variable | C18: Calculated Value | D18: Format | E18: Description
B19: Calc_LTV_Flag | C19: =IF(N(C12)=0,"N/A",IF(C12>C6,"Fail",IF(C12>=(C6-0.05),"Exception","Pass"))) -> N/A | D19: @ | E19: Pass / Exception (within 5% buffer) / Fail / N/A if no loan type selected
B20: Calc_LTC_Flag | C20: =IF(OR(N(C7)=0,N(C13)=0),"N/A",IF(C13>C7,"Fail",IF(C13>=(C7-0.05),"Exception","Pass"))) -> N/A | D20: @ | E20: Pass / Exception / Fail / N/A if not applicable for loan type (e.g. Bridge)
B21: Calc_LTARV_Flag | C21: =IF(OR(N(C8)=0,N(C15)=0),"N/A",IF(C15>C8,"Fail",IF(C15>=(C8-0.05),"Exception","Pass"))) -> N/A | D21: @ | E21: Pass / Exception / Fail / N/A if ARV field is blank
B22: Calc_Global_Elig | C22: =IF(OR(C19="Fail",C20="Fail",C21="Fail"),"Fail",IF(OR(C19="Exception",C20="Exception",C21="Exception"),"Exception Needed","Pass")) -> Pass | D22: @ | E22: OVERALL STATUS — drives the badge on 05_Quote_Summary
A24: SECTION 4 — PRICING ENGINE
B25: Variable | C25: Calculated Value | D25: Format | E25: Description
B26: Calc_Buy_Rate | C26: =IFERROR(INDEX('03_Pricing_&_Assumptions'!$C$19:$I$25,MATCH(N('02_Inputs'!$C$18),'03_Pricing_&_Assumptions'!$B$19:$B$25,1),MATCH(C12,'03_Pricing_&_Assumptions'!$C$18:$I$18,1)),"Check Risk Rules") -> Check Risk Rules | D26: 0.00% | E26: MATCH(FICO, tiers, ≤) × MATCH(Actual_LTV, tiers, ≤) → INDEX into buy rate grid
B27: Calc_Spread | C27: =IF(ISNUMBER(C26),'02_Inputs'!$C$15-C26,0) -> 0 | D27: 0.00% | E27: Note Rate minus Buy Rate = lender gross margin
B28: Calc_Spread_Status | C28: =IF(ISNUMBER(C26),IF(C27<'03_Pricing_&_Assumptions'!$C$13,"Below Margin","Valid"),"N/A") -> N/A | D28: @ | E28: Valid if Spread ≥ Asm_Min_Spread; otherwise Below Margin
B29: Calc_Spread_Deficit | C29: =IF(C28="Below Margin",'03_Pricing_&_Assumptions'!$C$13-C27,0) -> 0 | D29: 0.00% | E29: Shortfall below Min Spread Floor; 0 if margin is valid
A31: SECTION 5 — SETTLEMENT CALCULATIONS
B32: Variable | C32: Calculated Value | D32: Format | E32: Description
B33: Calc_Serv_Fee_Amt | C33: =IF(N('02_Inputs'!$C$14)=0,0,'02_Inputs'!$C$14*('03_Pricing_&_Assumptions'!$C$14/12)*N('02_Inputs'!$C$23)) -> 0 | D33: $#,##0.00 | E33: Loan Amt × (Annual Serv Fee ÷ 12) × Term Months
B34: Calc_Short_Interest | C34: =IF(N('02_Inputs'!$C$14)=0,0,'02_Inputs'!$C$14*('02_Inputs'!$C$15/360)*N('02_Inputs'!$C$24)) -> 0 | D34: $#,##0.00 | E34: Loan Amt × (Note Rate ÷ 360) × Short Int Days [Actual/360 convention]
B35: Calc_Net_Funding | C35: ='02_Inputs'!$C$14-C34-C33 -> 0 | D35: $#,##0.00 | E35: Gross Loan Amount minus Short Interest minus Servicing Fee Reserve
B36: Calc_Cash_To_Close | C36: =MAX(0,('02_Inputs'!$C$8+'02_Inputs'!$C$10)-C35) -> 0 | D36: $#,##0.00 | E36: MAX(0, Total Project Cost minus Net Funding to Borrower)
B37: Calc_Liq_Shortfall | C37: =MAX(0,C36-'02_Inputs'!$C$20) -> 0 | D37: $#,##0.00 | E37: MAX(0, Cash-to-Close minus Verified Liquid Assets)
A39: SECTION 6 — LENDER PROFIT EVALUATION ⚠ INTERNAL ONLY — NOT SURFACED ON QUOTE SUMMARY
B40: Variable | C40: Calculated Value | D40: Format | E40: Description
B41: Calc_Lender_Profit | C41: =IF(ISNUMBER(C26),'02_Inputs'!$C$14*C27*('02_Inputs'!$C$23/12),0) -> 0 | D41: $#,##0.00 | E41: Loan Amount × Spread × (Term Months ÷ 12) = estimated gross lender profit
B43: ⚠ WIREFRAME: Sheet 04 must be set to xlSheetVeryHidden, all formula cells set to Locked+Hidden, and sheet protected with admin password. See 01_ReadMe → Admin Actions.

Sheet 05_Quote_Summary
A1: RESIDENTIAL TRANSITIONAL LOAN · INDICATIVE TERM SHEET
A2: ='02_Inputs'!$C$5&" LOAN — INDICATIVE PRICING" -> Bridge LOAN — INDICATIVE PRICING | D2: Date Prepared: | E2: =TODAY() -> 46183
A4: OVERALL ELIGIBILITY STATUS
A5: =UPPER('04_Calc_Engine'!$C$22) -> PASS
A7: LOAN TERMS
B8: Loan Amount | D8: ='02_Inputs'!$C$14 -> 0
B9: Borrower Interest Rate | D9: ='02_Inputs'!$C$15 -> 0
B10: Loan Term | D10: ='02_Inputs'!$C$23&" Months" -> Months
B11: Loan Type | D11: ='02_Inputs'!$C$5 -> Bridge
A13: LEVERAGE METRICS
B14: Metric | C14: Actual | D14: Maximum Allowed | E14: Status
B15: Loan-to-Value (LTV) | C15: ='04_Calc_Engine'!$C$12 -> 0 | D15: ='04_Calc_Engine'!$C$6 -> 0 | E15: ='04_Calc_Engine'!$C$19 -> N/A
B16: Loan-to-Cost (LTC) | C16: ='04_Calc_Engine'!$C$13 -> 0 | D16: ='04_Calc_Engine'!$C$7 -> N/A | E16: ='04_Calc_Engine'!$C$20 -> N/A
B17: Loan-to-Purchase (LTP) | C17: ='04_Calc_Engine'!$C$14 -> 0 | D17: N/A | E17: N/A
B18: Loan-to-ARV (LTARV) | C18: ='04_Calc_Engine'!$C$15 -> 0 | D18: ='04_Calc_Engine'!$C$8 -> N/A | E18: ='04_Calc_Engine'!$C$21 -> N/A
A20: SETTLEMENT SUMMARY
B21: Prepaid Short Interest | D21: ='04_Calc_Engine'!$C$34 -> 0
B22: Servicing Fee Reserve | D22: ='04_Calc_Engine'!$C$33 -> 0
B23: Net Funding to Borrower | D23: ='04_Calc_Engine'!$C$35 -> 0
B24: Cash-to-Close Required | D24: ='04_Calc_Engine'!$C$36 -> 0
B25: Liquidity Shortfall | D25: ='04_Calc_Engine'!$C$37 -> 0
A27: BORROWER PROFILE
B28: FICO Score | D28: ='02_Inputs'!$C$18 -> 0
B29: Experience Tier | D29: ='02_Inputs'!$C$19 -> 0
B30: Verified Liquid Assets | D30: ='02_Inputs'!$C$20 -> 0
A32: DISCLAIMER: This document is indicative only and does not constitute a commitment to lend. All terms are subject to final underwriting review, independent appraisal, title examination, and lender credit approval. Confidential.
A33: ⚠ WIREFRAME NOTE (DELETE BEFORE DISTRIBUTING): Verify print area A1:E32 via File → Export → PDF. Confirm no Buy Rate, Spread, or Lender Profit data appears.
